odoo/addons/hr_timesheet_sheet_period/README.rst
odoo/addons/hr_timesheet_sheet_period/__init__.py
odoo/addons/hr_timesheet_sheet_period/__manifest__.py
odoo/addons/hr_timesheet_sheet_period/i18n/de.po
odoo/addons/hr_timesheet_sheet_period/i18n/es.po
odoo/addons/hr_timesheet_sheet_period/i18n/hr_timesheet_sheet_period.pot
odoo/addons/hr_timesheet_sheet_period/i18n/it.po
odoo/addons/hr_timesheet_sheet_period/i18n/pt.po
odoo/addons/hr_timesheet_sheet_period/migrations/12.0.2.0.0/post-upgrade.py
odoo/addons/hr_timesheet_sheet_period/models/__init__.py
odoo/addons/hr_timesheet_sheet_period/models/hr_timesheet_sheet.py
odoo/addons/hr_timesheet_sheet_period/models/res_company.py
odoo/addons/hr_timesheet_sheet_period/readme/CONFIGURE.rst
odoo/addons/hr_timesheet_sheet_period/readme/CONTRIBUTORS.rst
odoo/addons/hr_timesheet_sheet_period/readme/DESCRIPTION.rst
odoo/addons/hr_timesheet_sheet_period/readme/USAGE.rst
odoo/addons/hr_timesheet_sheet_period/static/description/icon.png
odoo/addons/hr_timesheet_sheet_period/static/description/index.html
odoo/addons/hr_timesheet_sheet_period/tests/__init__.py
odoo/addons/hr_timesheet_sheet_period/tests/test_hr_timesheet_sheet_period.py
odoo/addons/hr_timesheet_sheet_period/views/hr_timesheet_sheet_view.xml
odoo12_addon_hr_timesheet_sheet_period-12.0.2.0.0.99.dev22.dist-info/METADATA
odoo12_addon_hr_timesheet_sheet_period-12.0.2.0.0.99.dev22.dist-info/WHEEL
odoo12_addon_hr_timesheet_sheet_period-12.0.2.0.0.99.dev22.dist-info/top_level.txt
odoo12_addon_hr_timesheet_sheet_period-12.0.2.0.0.99.dev22.dist-info/RECORD
